picnik.py
picnik_v0.1.9-0.1.9.dist-info/LICENSE
picnik_v0.1.9-0.1.9.dist-info/WHEEL
picnik_v0.1.9-0.1.9.dist-info/METADATA
picnik_v0.1.9-0.1.9.dist-info/RECORD
