Metadata-Version: 2.1
Name: picnik-v0.1.9
Version: 0.1.9
Summary: A package to make isoconversional computations for non-isothermal kinetics
Home-page: https://github.com/ErickErock/pICNIK
License: MIT
Keywords: non-isothermal kinetics,isoconversion,isoconversional computations
Author: ErickErock
Author-email: ramirez.orozco.erick@gmail.com
Requires-Python: >=3.7,<4.0
Classifier: License :: OSI Approved :: MIT License
Classifier: Programming Language :: Python :: 3
Classifier: Programming Language :: Python :: 3.7
Classifier: Programming Language :: Python :: 3.8
Classifier: Programming Language :: Python :: 3.9
Requires-Dist: derivative
Requires-Dist: matplotlib (>=3.1.2,<4.0.0)
Requires-Dist: numpy (>=1.19.1,<2.0.0)
Requires-Dist: pandas (>=1.2.2,<2.0.0)
Requires-Dist: scipy (>=1.6.3,<2.0.0)
Project-URL: Repository, https://github.com/ErickErock/pICNIK
